acro_gos_utility.py
gcli.py
gcli_context.py
gcli_logging.py
gcli_util.py
setup.py
ntnx_gcli.egg-info/PKG-INFO
ntnx_gcli.egg-info/SOURCES.txt
ntnx_gcli.egg-info/dependency_links.txt
ntnx_gcli.egg-info/entry_points.txt
ntnx_gcli.egg-info/requires.txt
ntnx_gcli.egg-info/top_level.txt