Metadata-Version: 1.0
Name: ntnx-gcli
Version: 0.1
Summary: NTNX Guest OS Client tool
Home-page: https://drt-it-github-prod-1.eng.nutanix.com/hackathon-2017/main-clone/tree/guest_os_client/qa/tools/guest_os_client
Author: Amir Eibagi
Author-email: amir.eibagi@nutanix.com
License: UNKNOWN
Platform: UNKNOWN
